eggnest/__init__.py
eggnest/auth.py
eggnest/cli.py
eggnest/config.py
eggnest/household.py
eggnest/models.py
eggnest/mortality.py
eggnest/returns.py
eggnest/simulation.py
eggnest/ss_timing.py
eggnest/supabase_client.py
eggnest/sync.py
eggnest/tax.py
eggnest-0.1.0.dist-info/METADATA
eggnest-0.1.0.dist-info/WHEEL
eggnest-0.1.0.dist-info/entry_points.txt
eggnest-0.1.0.dist-info/RECORD
