Metadata-Version: 2.4
Name: eggnest
Version: 0.1.0
Summary: EggNest - Monte Carlo financial planning with real tax calculations
Author-email: EggNest <hello@eggnest.co>
License: MIT
Keywords: cli,finance,monte-carlo,planning,retirement,simulation
Requires-Python: >=3.11
Requires-Dist: click>=8.0
Requires-Dist: fastapi>=0.109.0
Requires-Dist: httpx>=0.26.0
Requires-Dist: numpy-financial>=1.0.0
Requires-Dist: numpy>=1.24.0
Requires-Dist: pandas>=2.0.0
Requires-Dist: policyengine-us>=1.0.0
Requires-Dist: pydantic-settings>=2.1.0
Requires-Dist: pydantic>=2.5.0
Requires-Dist: pyyaml>=6.0
Requires-Dist: rich>=13.0
Requires-Dist: scipy>=1.10.0
Requires-Dist: uvicorn[standard]>=0.27.0
Provides-Extra: cli
Requires-Dist: python-jose[cryptography]>=3.3.0; extra == 'cli'
Requires-Dist: supabase>=2.0.0; extra == 'cli'
Provides-Extra: dev
Requires-Dist: black>=23.0.0; extra == 'dev'
Requires-Dist: mypy>=1.5.0; extra == 'dev'
Requires-Dist: pytest-asyncio>=0.23.0; extra == 'dev'
Requires-Dist: pytest-cov>=4.1.0; extra == 'dev'
Requires-Dist: pytest>=7.4.0; extra == 'dev'
Requires-Dist: ruff>=0.1.0; extra == 'dev'
Provides-Extra: enhanced
Requires-Dist: arch>=6.0.0; extra == 'enhanced'
Requires-Dist: statsmodels>=0.14.0; extra == 'enhanced'
Requires-Dist: yfinance>=0.2.0; extra == 'enhanced'
